range_coding.cpython-312-i386-linux-gnu.so
src/range_coding_cython/range_coding.py
src/range_coding_cython/py.typed
src/range_coding_cython/__init__.py
range_coding_cython-0.1.0.dist-info/WHEEL
range_coding_cython-0.1.0.dist-info/RECORD
range_coding_cython-0.1.0.dist-info/top_level.txt
range_coding_cython-0.1.0.dist-info/METADATA
range_coding_cython-0.1.0.dist-info/licenses/LICENSE
