Metadata-Version: 2.4
Name: range-coding-cython
Version: 0.1.0
Summary: A range coding lib implemented in Cython
Author-email: Namoe <yangziming@buaa.edu.cn>
Requires-Python: >=3.12
License-File: LICENSE
Requires-Dist: cython>=3.0.12
Dynamic: license-file
